[{"hour": "0", "status_id": "1", "color": "#e6e6e6", "status_name": "7alawa", "road_id": "289", "new": "0", "minute": "46", "name": "Da2ery;Wa7at Road To Nazlet Sa7rawy"}, {"hour": "0", "status_id": "1", "color": "#e6e6e6", "status_name": "7alawa", "road_id": "477", "new": "0", "minute": "46", "name": "Da2ery;Sa7rawy To Waslet Maryoutia"}, {"hour": "0", "status_id": "1", "color": "#e6e6e6", "status_name": "7alawa", "road_id": "478", "new": "0", "minute": "44", "name": "El Wasla; To Moneeb Direction"}, {"hour": "0", "status_id": "1", "color": "#e6e6e6", "status_name": "7alawa", "road_id": "125", "new": "0", "minute": "41", "name": "Da2ery;Waslet Maryoutia To Moneeb"}, {"hour": "0", "status_id": "2", "color": "#e6e6e6", "status_name": "lazeez", "road_id": "32", "new": "0", "minute": "35", "name": "Da2ery;Moneeb To Autostrad"}, {"hour": "1", "status_id": "1", "color": "#e6e6e6", "status_name": "7alawa", "road_id": "281", "new": "0", "minute": "59", "name": "Da2ery;Autostrad To Sokhna Exit"}, {"hour": "1", "status_id": "1", "color": "#e6e6e6", "status_name": "7alawa", "road_id": "315", "new": "0", "minute": "47", "name": "Da2ery;Sokhna Exit To Tagamo3"}, {"hour": "1", "status_id": "1", "color": "#e6e6e6", "status_name": "7alawa", "road_id": "316", "new": "0", "minute": "25", "name": "Da2ery;Tagamo3 To Suez Rd."}, {"hour": "1", "status_id": "1", "color": "#e6e6e6", "status_name": "7alawa", "road_id": "302", "new": "0", "minute": "25", "name": "Da2ery;Suez Rd. To Nafa2 ElSalam"}, {"hour": "1", "status_id": "1", "color": "#e6e6e6", "status_name": "7alawa", "road_id": "285", "new": "0", "minute": "25", "name": "Da2ery;Nafa2 ElSalam To Zera3y"}, {"hour": "1", "status_id": "1", "color": "#e6e6e6", "status_name": "7alawa", "road_id": "284", "new": "0", "minute": "25", "name": "Da2ery;Zera3y To Nafa2 ElSalam"}, {"hour": "1", "status_id": "1", "color": "#e6e6e6", "status_name": "7alawa", "road_id": "301", "new": "0", "minute": "25", "name": "Da2ery;Nafa2 ElSalam To Suez Rd."}, {"hour": "1", "status_id": "1", "color": "#e6e6e6", "status_name": "7alawa", "road_id": "317", "new": "0", "minute": "25", "name": "Da2ery;Suez Rd. To Tagamo3"}, {"hour": "1", "status_id": "1", "color": "#e6e6e6", "status_name": "7alawa", "road_id": "318", "new": "0", "minute": "24", "name": "Da2ery;Tagamo3 To Sokhna Exit"}, {"hour": "1", "status_id": "1", "color": "#e6e6e6", "status_name": "7alawa", "road_id": "282", "new": "0", "minute": "24", "name": "Da2ery;Sokhna Exit To Autostrad"}, {"hour": "1", "status_id": "1", "color": "#e6e6e6", "status_name": "7alawa", "road_id": "31", "new": "0", "minute": "43", "name": "Da2ery;Autostrad To Moneeb"}, {"hour": "1", "status_id": "1", "color": "#e6e6e6", "status_name": "7alawa", "road_id": "126", "new": "0", "minute": "24", "name": "Da2ery;Moneeb To Waslet Maryoutia"}, {"hour": "1", "status_id": "1", "color": "#E6E6E6", "status_name": "7alawa", "road_id": "601", "new": "1", "minute": "24", "name": "Da2ery;Maryouteya To Mansoureya"}, {"hour": "1", "status_id": "1", "color": "#e6e6e6", "status_name": "7alawa", "road_id": "204", "new": "0", "minute": "23", "name": "Mansoureya;Da2ery To Haram"}, {"hour": "1", "status_id": "1", "color": "#e6e6e6", "status_name": "7alawa", "road_id": "474", "new": "0", "minute": "23", "name": "El Wasla; To Sa7rawy Direction"}, {"hour": "1", "status_id": "1", "color": "#e6e6e6", "status_name": "7alawa", "road_id": "475", "new": "0", "minute": "23", "name": "Da2ery;Waslet Maryoutia To Sa7rawy"}, {"hour": "1", "status_id": "1", "color": "#E6E6E6", "status_name": "7alawa", "road_id": "291", "new": "0", "minute": "23", "name": "Da2ery;Nazlet Sa7rawy To Pyramids Heights (Hazem Hassan Previously)"}, {"hour": "1", "status_id": "1", "color": "#e6e6e6", "status_name": "7alawa", "road_id": "292", "new": "0", "minute": "23", "name": "Da2ery;Nazlet Sa7rawy To Wa7at Rd."}, {"hour": "1", "status_id": "1", "color": "#e6e6e6", "status_name": "7alawa", "road_id": "121", "new": "0", "minute": "23", "name": "Da2ery;Waslet Maryoutia To Me7war"}, {"hour": "1", "status_id": "1", "color": "#e6e6e6", "status_name": "7alawa", "road_id": "283", "new": "0", "minute": "22", "name": "Da2ery;Me7war To Zera3y"}, {"hour": "1", "status_id": "1", "color": "#e6e6e6", "status_name": "7alawa", "road_id": "286", "new": "0", "minute": "22", "name": "Da2ery;Zera3y To Me7war"}, {"hour": "1", "status_id": "1", "color": "#e6e6e6", "status_name": "7alawa", "road_id": "122", "new": "0", "minute": "22", "name": "Da2ery;Me7war To Waslet Maryoutia"}, {"hour": "1", "status_id": "1", "color": "#e6e6e6", "status_name": "7alawa", "road_id": "174", "new": "0", "minute": "6", "name": "Sala7 Salem;Kobry 6 October To Matar"}, {"hour": "1", "status_id": "1", "color": "#e6e6e6", "status_name": "7alawa", "road_id": "201", "new": "0", "minute": "22", "name": "Wahat Road;October To Fayoum Road"}, {"hour": "1", "status_id": "1", "color": "#e6e6e6", "status_name": "7alawa", "road_id": "200", "new": "0", "minute": "22", "name": "Wahat Road;Fayoum Road To October"}, {"hour": "0", "status_id": "2", "color": "#e6e6e6", "status_name": "lazeez", "road_id": "151", "new": "0", "minute": "2", "name": "Zera3y Road;Alex To Cairo"}]